print_tricks/__init__.py
print_tricks_and_more-2025.7.27.142.dist-info/METADATA
print_tricks_and_more-2025.7.27.142.dist-info/WHEEL
print_tricks_and_more-2025.7.27.142.dist-info/top_level.txt
print_tricks_and_more-2025.7.27.142.dist-info/RECORD
