Metadata-Version: 2.1
Name: print-tricks-and-more
Version: 2025.7.27.142
Summary: Simple to use, Powerful Programming! Debugging, Printing, Analysis, and helpful tools!
Home-page: https://github.com/developer-1v/print_tricks
Author: developer-1v
Author-email: developer-1v <developer_1v@proton.me>
License: MIT
Project-URL: Homepage, https://github.com/developer-1v/print_tricks
Project-URL: Bug Tracker, https://github.com/developer-1v/print_tricks/issues
Project-URL: Documentation, https://github.com/developer-1v/print_tricks
Project-URL: Source Code, https://github.com/developer-1v/print_tricks
Classifier: Programming Language :: Python :: 3
Classifier: Programming Language :: Python :: 3.6
Classifier: Programming Language :: Python :: 3.7
Classifier: Programming Language :: Python :: 3.8
Classifier: Programming Language :: Python :: 3.9
Classifier: Programming Language :: Python :: 3.10
Classifier: Programming Language :: Python :: 3.11
Classifier: License :: OSI Approved :: MIT License
Classifier: Operating System :: OS Independent
Classifier: Development Status :: 4 - Beta
Classifier: Intended Audience :: Developers
Classifier: Topic :: Software Development :: Debuggers
Classifier: Topic :: Software Development :: Libraries :: Python Modules
Requires-Python: >=3.6
